windowsapps/__init__.py
windowsapps-0.0.9.dist-info/LICENSE
windowsapps-0.0.9.dist-info/METADATA
windowsapps-0.0.9.dist-info/WHEEL
windowsapps-0.0.9.dist-info/top_level.txt
windowsapps-0.0.9.dist-info/RECORD
