Metadata-Version: 2.1
Name: windowsapps
Version: 0.0.9
Summary: Windows Apps for python
Home-page: https://github.com/StealtherThreat/windowsapps
Author: Tushar Goyal
Author-email: StealtherThreat@outlook.com
License: UNKNOWN
Platform: UNKNOWN
Classifier: Programming Language :: Python :: 3
Classifier: License :: OSI Approved :: MIT License
Classifier: Operating System :: Microsoft :: Windows :: Windows 10
Requires-Python: >=3.6
License-File: LICENSE
